ZephyrTask/__init__.py
ZephyrTask/tasks.py
zephyrtask-0.1.4.dist-info/licenses/LICENSE
zephyrtask-0.1.4.dist-info/METADATA
zephyrtask-0.1.4.dist-info/WHEEL
zephyrtask-0.1.4.dist-info/top_level.txt
zephyrtask-0.1.4.dist-info/RECORD
