Metadata-Version: 2.4
Name: ZephyrTask
Version: 0.1.4
Summary: A simple task management package
Author-email: Xingjian <xz3954@nyu.edu>, Lan <ly2238@nyu.edu>, Yuquan <yh4663@nyu.edu>, Yilei <yw6929@nyu.edu>
License:                     GNU GENERAL PUBLIC LICENSE
Project-URL: Homepage, https://github.com/software-students-spring2025/3-python-package-super-package
Project-URL: Bug Tracker, https://github.com/software-students-spring2025/3-python-package-super-package/issues
Classifier: Programming Language :: Python :: 3
Classifier: Programming Language :: Python :: 3.7
Classifier: Programming Language :: Python :: 3.8
Classifier: Programming Language :: Python :: 3.9
Classifier: Programming Language :: Python :: 3.10
Classifier: License :: OSI Approved :: MIT License
Classifier: Operating System :: OS Independent
Requires-Python: >=3.7
License-File: LICENSE
Requires-Dist: pyjokes>=0.6.0
Dynamic: license-file
